<?xml version="1.0" encoding="UTF-8" standalone="yes"?>
<unit xmlns="http://www.srcML.org/srcML/src" revision="1.0.0" language="Java" filename="E:/01Courses@USASK/CMPT898-HumanDrivenSoftwareEngineeringForScientificResearch/ProjectProgress/data_files/final_dataset/gen_patch_codes/filtered/ambari/288573dcea.java"><expr_stmt><expr><name>From</name> <literal type="number">288573dceaf6a82f3d671186e766688d53407028</literal> <name>Mon</name> <name>Sep</name> <literal type="number">17</literal> <literal type="number">00</literal><operator>:</operator><literal type="number">00</literal><operator>:</operator><literal type="number">00</literal> <literal type="number">2001</literal>
<name>From</name><operator>:</operator> <name>Myroslav</name> <name><name>Papirkovskyi</name> <argument_list type="generic">&lt;<argument><name>mpapyrkovskyy</name><annotation>@<name><name>hortonworks</name><operator>.</operator><name>com</name></name></annotation></argument>&gt;</argument_list></name>
<name>Date</name><operator>:</operator> <name>Tue</name></expr><operator>,</operator> <expr><literal type="number">23</literal> <name>Aug</name> <literal type="number">2016</literal> <literal type="number">19</literal><operator>:</operator><literal type="number">09</literal><operator>:</operator><literal type="number">04</literal> <operator>+</operator><literal type="number">0300</literal>
<name>Subject</name><operator>:</operator> <index>[<expr><name>PATCH</name></expr>]</index> <name>AMBARI</name><operator>-</operator><literal type="number">18104.</literal> <name>Unit</name> <name>Tests</name> <name>Broken</name> <name>Due</name> <name>to</name> <name>AMBARI</name><operator>-</operator><literal type="number">18011.</literal>
 <operator>(</operator><name>mpapirkovskyy</name><operator>)</operator>

<operator>--</operator>
 <operator>...</operator><operator>/</operator><name>dao</name><operator>/</operator><name><name>ServiceComponentDesiredStateDAO</name><operator>.</operator><name>java</name></name>  <operator>|</operator>  <literal type="number">2</literal> <operator>+</operator><operator>-</operator>
 <operator>...</operator><operator>/</operator><name><name>AmbariManagementControllerTest</name><operator>.</operator><name>java</name></name>       <operator>|</operator> <literal type="number">19</literal> <operator>--</operator><operator>--</operator><operator>--</operator><operator>--</operator><operator>--</operator><operator>--</operator><operator>--</operator><operator>--</operator><operator>--</operator><operator>-</operator>
 <literal type="number">2</literal> <name>files</name> <name>changed</name></expr><operator>,</operator> <expr><literal type="number">1</literal> <call><name>insertion</name><argument_list>(<argument><expr><operator>+</operator></expr></argument>)</argument_list></call></expr><operator>,</operator> <expr><literal type="number">20</literal> <call><name>deletions</name><argument_list>(<argument><expr><operator>-</operator></expr></argument>)</argument_list></call>

<name>diff</name> <operator>--</operator><name>git</name> <name>a</name><operator>/</operator><name>ambari</name><operator>-</operator><name>server</name><operator>/</operator><name>src</name><operator>/</operator><name>main</name><operator>/</operator><name>java</name><operator>/</operator><name>org</name><operator>/</operator><name>apache</name><operator>/</operator><name>ambari</name><operator>/</operator><name>server</name><operator>/</operator><name>orm</name><operator>/</operator><name>dao</name><operator>/</operator><name><name>ServiceComponentDesiredStateDAO</name><operator>.</operator><name>java</name></name> <name>b</name><operator>/</operator><name>ambari</name><operator>-</operator><name>server</name><operator>/</operator><name>src</name><operator>/</operator><name>main</name><operator>/</operator><name>java</name><operator>/</operator><name>org</name><operator>/</operator><name>apache</name><operator>/</operator><name>ambari</name><operator>/</operator><name>server</name><operator>/</operator><name>orm</name><operator>/</operator><name>dao</name><operator>/</operator><name><name>ServiceComponentDesiredStateDAO</name><operator>.</operator><name>java</name></name>
<name>index</name> <literal type="number">4c906cc489</literal><operator>..</operator><name>cdaa6f0aaf</name> <literal type="number">100644</literal>
<operator>--</operator> <name>a</name><operator>/</operator><name>ambari</name><operator>-</operator><name>server</name><operator>/</operator><name>src</name><operator>/</operator><name>main</name><operator>/</operator><name>java</name><operator>/</operator><name>org</name><operator>/</operator><name>apache</name><operator>/</operator><name>ambari</name><operator>/</operator><name>server</name><operator>/</operator><name>orm</name><operator>/</operator><name>dao</name><operator>/</operator><name><name>ServiceComponentDesiredStateDAO</name><operator>.</operator><name>java</name></name>
<operator>++</operator> <name>b</name><operator>/</operator><name>ambari</name><operator>-</operator><name>server</name><operator>/</operator><name>src</name><operator>/</operator><name>main</name><operator>/</operator><name>java</name><operator>/</operator><name>org</name><operator>/</operator><name>apache</name><operator>/</operator><name>ambari</name><operator>/</operator><name>server</name><operator>/</operator><name>orm</name><operator>/</operator><name>dao</name><operator>/</operator><name><name>ServiceComponentDesiredStateDAO</name><operator>.</operator><name>java</name></name>
@@ <operator>-</operator><literal type="number">117</literal></expr><operator>,</operator><expr><literal type="number">7</literal> <operator>+</operator><literal type="number">117</literal></expr><operator>,</operator><expr><literal type="number">7</literal> @@ <specifier>public</specifier> <name>class</name> <name>ServiceComponentDesiredStateDAO</name> <block>{
 
   @<expr><name>Transactional</name>
   <specifier>public</specifier> <name>void</name> <call><name>remove</name><argument_list>(<argument><expr><name>ServiceComponentDesiredStateEntity</name> <name>serviceComponentDesiredStateEntity</name></expr></argument>)</argument_list></call> <block>{
    <expr><call><name><name>entityManagerProvider</name><operator>.</operator><name>get</name></name><argument_list>()</argument_list></call><operator>.</operator><call><name>remove</name><argument_list>(<argument><expr><call><name>merge</name><argument_list>(<argument><expr><name>serviceComponentDesiredStateEntity</name></expr></argument>)</argument_list></call></expr></argument>)</argument_list></call></expr>;
    <expr><call><name><name>entityManagerProvider</name><operator>.</operator><name>get</name></name><argument_list>()</argument_list></call><operator>.</operator><call><name>remove</name><argument_list>(<argument><expr><name>serviceComponentDesiredStateEntity</name></expr></argument>)</argument_list></call></expr>;
   }</block>
 
   @<name>Transactional</name>
<name>diff</name> <operator>--</operator><name>git</name> <name>a</name><operator>/</operator><name>ambari</name><operator>-</operator><name>server</name><operator>/</operator><name>src</name><operator>/</operator><name>test</name><operator>/</operator><name>java</name><operator>/</operator><name>org</name><operator>/</operator><name>apache</name><operator>/</operator><name>ambari</name><operator>/</operator><name>server</name><operator>/</operator><name>controller</name><operator>/</operator><name><name>AmbariManagementControllerTest</name><operator>.</operator><name>java</name></name> <name>b</name><operator>/</operator><name>ambari</name><operator>-</operator><name>server</name><operator>/</operator><name>src</name><operator>/</operator><name>test</name><operator>/</operator><name>java</name><operator>/</operator><name>org</name><operator>/</operator><name>apache</name><operator>/</operator><name>ambari</name><operator>/</operator><name>server</name><operator>/</operator><name>controller</name><operator>/</operator><name><name>AmbariManagementControllerTest</name><operator>.</operator><name>java</name></name>
<name>index</name> <name>f8e891b781</name><operator>..</operator><literal type="number">3e3f1d60ae</literal> <literal type="number">100644</literal>
<operator>--</operator> <name>a</name><operator>/</operator><name>ambari</name><operator>-</operator><name>server</name><operator>/</operator><name>src</name><operator>/</operator><name>test</name><operator>/</operator><name>java</name><operator>/</operator><name>org</name><operator>/</operator><name>apache</name><operator>/</operator><name>ambari</name><operator>/</operator><name>server</name><operator>/</operator><name>controller</name><operator>/</operator><name><name>AmbariManagementControllerTest</name><operator>.</operator><name>java</name></name>
<operator>++</operator> <name>b</name><operator>/</operator><name>ambari</name><operator>-</operator><name>server</name><operator>/</operator><name>src</name><operator>/</operator><name>test</name><operator>/</operator><name>java</name><operator>/</operator><name>org</name><operator>/</operator><name>apache</name><operator>/</operator><name>ambari</name><operator>/</operator><name>server</name><operator>/</operator><name>controller</name><operator>/</operator><name><name>AmbariManagementControllerTest</name><operator>.</operator><name>java</name></name>
@@ <operator>-</operator><literal type="number">9280</literal></expr>,<expr><literal type="number">25</literal> <operator>+</operator><literal type="number">9280</literal></expr>,<expr><literal type="number">6</literal> @@ <specifier>public</specifier> <name>class</name> <name>AmbariManagementControllerTest</name> <block>{
   @<expr><name>Test</name>
   <specifier>public</specifier> <name>void</name> <call><name>testDeleteClusterCreateHost</name><argument_list>()</argument_list></call> <throws>throws <argument><expr><name>Exception</name> <block>{
 
    <expr><name>Injector</name> <name>injector</name> <operator>=</operator> <call><name><name>Guice</name><operator>.</operator><name>createInjector</name></name><argument_list>(<argument><expr><operator>new</operator> <call><name>AuditLoggerModule</name><argument_list>()</argument_list></call></expr></argument>, <argument><expr><operator>new</operator> <class><super><name>AbstractModule</name></super><argument_list>(</argument_list></class></expr></argument>)</argument_list></call> <block>{
      <expr><annotation>@<name>Override</name></annotation>
      <specifier>protected</specifier> <name>void</name> <call><name>configure</name><argument_list>()</argument_list></call> <block>{
        <expr><name>Properties</name> <name>properties</name> <operator>=</operator> <operator>new</operator> <call><name>Properties</name><argument_list>()</argument_list></call></expr></block></expr></block></expr></block></expr></argument></throws></expr>;
        <expr><call><name><name>properties</name><operator>.</operator><name>setProperty</name></name><argument_list>(<argument><expr><call><name><name>Configuration</name><operator>.</operator><name>SERVER_PERSISTENCE_TYPE</name><operator>.</operator><name>getKey</name></name><argument_list>()</argument_list></call></expr></argument>, <argument><expr><literal type="string">"in-memory"</literal></expr></argument>)</argument_list></call></expr>;

        <expr><call><name><name>properties</name><operator>.</operator><name>setProperty</name></name><argument_list>(<argument><expr><call><name><name>Configuration</name><operator>.</operator><name>METADATA_DIR_PATH</name><operator>.</operator><name>getKey</name></name><argument_list>()</argument_list></call></expr></argument>,<argument><expr><literal type="string">"src/test/resources/stacks"</literal></expr></argument>)</argument_list></call></expr>;
        <expr><call><name><name>properties</name><operator>.</operator><name>setProperty</name></name><argument_list>(<argument><expr><call><name><name>Configuration</name><operator>.</operator><name>SERVER_VERSION_FILE</name><operator>.</operator><name>getKey</name></name><argument_list>()</argument_list></call></expr></argument>,<argument><expr><literal type="string">"../version"</literal></expr></argument>)</argument_list></call></expr>;
        <expr><call><name><name>properties</name><operator>.</operator><name>setProperty</name></name><argument_list>(<argument><expr><call><name><name>Configuration</name><operator>.</operator><name>OS_VERSION</name><operator>.</operator><name>getKey</name></name><argument_list>()</argument_list></call></expr></argument>, <argument><expr><literal type="string">"centos6"</literal></expr></argument>)</argument_list></call></expr>;
        <expr><call><name><name>properties</name><operator>.</operator><name>setProperty</name></name><argument_list>(<argument><expr><call><name><name>Configuration</name><operator>.</operator><name>SHARED_RESOURCES_DIR</name><operator>.</operator><name>getKey</name></name><argument_list>()</argument_list></call></expr></argument>, <argument><expr><literal type="string">"src/test/resources/"</literal></expr></argument>)</argument_list></call></expr>;
        <try>try <block>{<block_content>
          <expr_stmt><expr><call><name>install</name><argument_list>(<argument><expr><operator>new</operator> <call><name>ControllerModule</name><argument_list>(<argument><expr><name>properties</name></expr></argument>)</argument_list></call></expr></argument>)</argument_list></call></expr>;</expr_stmt>
        <expr_stmt/></block_content></block></try>}</block></expr> <catch>catch <parameter_list>(<parameter><decl><type><name>Exception</name></type> <name>e</name></decl></parameter>)</parameter_list> <block>{<block_content>
          <throw>throw <expr><operator>new</operator> <call><name>RuntimeException</name><argument_list>(<argument><expr><name>e</name></expr></argument>)</argument_list></call></expr>;</throw>
        <expr_stmt/></block_content></block></catch>}</block></expr></expr_stmt>
      }
    })<empty_stmt>;</empty_stmt>
    <expr_stmt><expr><call><name><name>injector</name><operator>.</operator><name>getInstance</name></name><argument_list>(<argument><expr><name><name>GuiceJpaInitializer</name><operator>.</operator><name>class</name></name></expr></argument>)</argument_list></call></expr>;</expr_stmt>

     <decl_stmt><decl><type><name>String</name></type> <name>STACK_ID</name> <init>= <expr><literal type="string">"HDP-2.0.1"</literal></expr></init></decl>;</decl_stmt>
 
     <decl_stmt><decl><type><name>String</name></type> <name>CLUSTER_NAME</name> <init>= <expr><call><name>getUniqueName</name><argument_list>()</argument_list></call></expr></init></decl>;</decl_stmt>
<expr><operator>-</operator> 
<literal type="number">2.19.1.windows</literal><literal type="number">.1</literal></expr>

</unit>
